django_rest_token_expiry/__init__.py
django_rest_token_expiry/authentication.py
django_rest_token_expiry-1.0.dist-info/LICENSE
django_rest_token_expiry-1.0.dist-info/METADATA
django_rest_token_expiry-1.0.dist-info/WHEEL
django_rest_token_expiry-1.0.dist-info/top_level.txt
django_rest_token_expiry-1.0.dist-info/RECORD
