Metadata-Version: 2.1
Name: django-rest-token-expiry
Version: 1.0
Summary: Django REST Token Expiry is a Python package designed to add token expiration functionality to Django REST Framework's default token authentication system. This package allows developers to set expiry durations for authentication tokens, enhancing security by automatically invalidating tokens after a specified period.
Home-page: https://github.com/joe-philip/django_rest_token_expiry.git
Author: Joe Philip
Author-email: joe.philip@hotmail.co.in
License: MIT License
Platform: UNKNOWN
Classifier: Environment :: Web Environment
Classifier: Framework :: Django
Classifier: Intended Audience :: Developers
Classifier: License :: OSI Approved :: MIT License
Classifier: Operating System :: OS Independent
Classifier: Programming Language :: Python
Classifier: Topic :: Internet :: WWW/HTTP
Classifier: Topic :: Software Development :: Libraries :: Application Frameworks
Requires-Dist: djangorestframework >=3.14.0
Requires-Dist: toml
